src/wb_simulator.sv
module wb_simulator #(
    parameter MEM_FILE = "memh_init.memh",
    parameter DEPTH = 1024,
    parameter LATENCY = 3
)(
    input  logic        clk,
    input  logic        rst_n,

    input  logic        req,       // asserted for one cycle to start a transaction
    input  logic        we,        // 0=read, 1=write
    input  logic [31:0] addr,
    input  logic [31:0] wdata,

    output logic [31:0] rdata,
    output logic        busy,      // high while operation is in progress
    output logic        valid      // high for one cycle when read completes
);
    // --- memory ---
    logic [31:0] mem [0:DEPTH-1];
    initial $readmemh(MEM_FILE, mem);

    // --- internal state ---
    logic [$clog2(LATENCY+1)-1:0] counter;
    logic pending;
    logic [31:0] addr_reg;

    // --- behavior ---
    always_ff @(posedge clk or negedge rst_n) begin
        if (!rst_n) begin
            counter <= '0;
            pending <= 0;
            busy    <= 0;
            valid   <= 0;
            rdata   <= 0;
        end else begin
            valid <= 0; // default

            if (req && !busy) begin
                // new request
                pending <= 1;
                busy    <= 1;
                counter <= LATENCY - 1;
                addr_reg <= addr;

                if (we)
                    mem[addr[31:2]] <= wdata; // immediate store
            end
            else if (pending) begin
                if (counter == 0) begin
                    pending <= 0;
                    busy    <= 0;
                    if (!we) begin
                        rdata <= mem[addr_reg[31:2]];
                        valid <= 1; // one-cycle pulse
                    end
                end else begin
                    counter <= counter - 1;
                end
            end
        end
    end
endmodule

src/icache.sv
module icache (
  input logic [31:0] addr,
  input logic send_pulse, clk, rst,
  output logic [31:0] inst,
  output logic ack
);

  //state machine for rewriting cache from new origin
  typedef enum {
    START_WRITE, 
    WAIT_BUSY,
    REWRITE,    
    IDLE_WRITE
  } write_state;

  //state machine for miss fetching with wishbone
  typedef enum {
    START_WB,
    POLL,
    IDLE_WB
  } wb_state;

  //state machine for hit
  typedef enum {
    REC,
    SEND
  } hit_state;

  write_state next_write, write;
  wb_state next_wb, wb;
  hit_state next_hit, hit;

  //internal signals
  logic [58:0] data [0:15]; //{valid, 26b tag, 32b inst}
  logic [58:0] next_data [0:15];
  logic [25:0] next_origin, origin; //origin of current cache instructions

  //wishbone signals for miss fetch
  logic req_solo, valid_solo; 
  logic [31:0] rdata_solo;

  //wishbone signals for cache rewrite
  logic req, valid_0, valid_1, valid_2, valid_3, busy_0, busy_1, busy_2, busy_3;
  logic [31:0] addr_0, addr_1, addr_2, addr_3;
  logic [31:0] rdata_0, rdata_1, rdata_2, rdata_3;

  //other signals
  logic [1:0] ct, next_ct; //4 wb, ct tracks 4 cycles of transactions to fill 16 instructions
  logic [3:0] idx, next_idx, reg_idx;
  logic [25:0] tag;
  logic ack_hit, ack_miss; //acks for when instruction is ready after hit and miss


  assign idx = addr [5:2];
  assign tag = addr [31:6];
  assign ack = ack_hit | ack_miss;

  always_comb begin
    //miss fetch signals
    ack_miss = 1'b0;
    next_wb = wb;
    req_solo = 1'b0;
    next_idx = idx;

    //start signals
    ack_hit = 1'b0;
    next_origin = origin;
    inst = '0;
    
    //cache rewrite signals
    req = 1'b0;
    next_ct = ct;
    next_write = write;
    addr_0 = '0;
    addr_1 = '0;
    addr_2 = '0;
    addr_3 = '0;
    next_data[0] = data[0];
    next_data[1] = data[1];
    next_data[2] = data[2];
    next_data[3] = data[3];
    next_data[4] = data[4];
    next_data[5] = data[5];
    next_data[6] = data[6];
    next_data[7] = data[7];
    next_data[8] = data[8];
    next_data[9] = data[9];
    next_data[10] = data[10];
    next_data[11] = data[11];
    next_data[12] = data[12];
    next_data[13] = data[13];
    next_data[14] = data[14];
    next_data[15] = data[15];

    next_hit = hit;

    //wb statemachine (for misses)
    case (wb)
      START_WB: begin
        req_solo = 1'b1;
        next_wb = POLL;
      end
      POLL: begin
        if (valid_solo) begin
          next_wb = IDLE_WB;
          inst = rdata_solo;
          ack_miss = 1'b1;
        end
      end
      default:;
    endcase
    
    //hit statemachine
    case (hit)
      REC: begin
        if (send_pulse) begin
          if (data[idx][58] && tag == data[idx][57:32]) begin //hit
            next_hit = SEND;
          end else begin //miss
            next_wb = START_WB;
            if (origin != tag || write == IDLE_WRITE) begin //if cache is not currently being rewritten in the correct frame, start rewriting
              next_write = START_WRITE; //this needs to be a complete restart, complete restart 
              next_origin = tag;
            end
          end
        end
      end
      SEND: begin //need registered
        next_hit = REC;
        inst = data[reg_idx][31:0];
        ack_hit = 1'b1;
      end
      default:;
    endcase


    //cache rewrite statemachine
    case (write)
      START_WRITE: begin
        if (busy_0 || busy_1 || busy_2 || busy_3) begin //cache rewrite in the middle of another rewrite
          next_ct = 2'b00;
          next_write = WAIT_BUSY;
        end else begin
          req = 1'b1;
          addr_0 = {origin, ct, 4'b0000};
          addr_1 = {origin, ct, 4'b0100};
          addr_2 = {origin, ct, 4'b1000};
          addr_3 = {origin, ct, 4'b1100};
          next_write = REWRITE;
        end
      end 
      WAIT_BUSY: if (valid_0 && valid_1 && valid_2 && valid_3) next_write = START_WRITE;
      REWRITE: begin
        if (valid_0 && valid_1 && valid_2 && valid_3) begin
          next_data[{ct, 2'b00}] = {1'b1, origin, rdata_0};
          next_data[{ct, 2'b01}] = {1'b1, origin, rdata_1};
          next_data[{ct, 2'b10}] = {1'b1, origin, rdata_2};
          next_data[{ct, 2'b11}] = {1'b1, origin, rdata_3};
          if (ct == 2'b11) begin //
            next_write = IDLE_WRITE;
            next_ct = '0;
          end else begin
            next_write = START_WRITE;
            next_ct = ct + 2'b01;
          end
        end
      end
      IDLE_WRITE: next_ct = 2'b00;
      default:;
    endcase
  end

  always_ff @(posedge clk or posedge rst) begin
    if (rst) begin
      origin <= '0;
      write <= IDLE_WRITE;
      wb <= IDLE_WB;
      hit <= REC;
      ct <= '0;
      reg_idx <= 4'b0;
      data[0] <= '0;
      data[1] <= '0;
      data[2] <= '0;
      data[3] <= '0;
      data[4] <= '0;
      data[5] <= '0;
      data[6] <= '0;
      data[7] <= '0;
      data[8] <= '0;
      data[9] <= '0;
      data[10] <= '0;
      data[11] <= '0;
      data[12] <= '0;
      data[13] <= '0;
      data[14] <= '0;
      data[15] <= '0;
    end else begin
      reg_idx <= next_idx;
      hit <= next_hit;
      origin <= next_origin;
      write <= next_write;
      wb <= next_wb;
      ct <= next_ct;
      data[0] = next_data[0];
      data[1] = next_data[1];
      data[2] = next_data[2];
      data[3] = next_data[3];
      data[4] = next_data[4];
      data[5] = next_data[5];
      data[6] = next_data[6];
      data[7] = next_data[7];
      data[8] = next_data[8];
      data[9] = next_data[9];
      data[10] = next_data[10];
      data[11] = next_data[11];
      data[12] = next_data[12];
      data[13] = next_data[13];
      data[14] = next_data[14];
      data[15] = next_data[15];
    end
  end

  //solo inst to get miss instr
  wb_simulator #(
    .MEM_FILE("instruction_memory.memh"),
    .DEPTH(1024),
    .LATENCY(3)
  ) wb_solo_inst (
    .clk(clk),
    .rst_n(~rst),
    .req(req_solo),
    .we(1'b0),
    .addr(addr),
    .wdata(32'd0),
    .rdata(rdata_solo),
    .busy(),
    .valid(valid_solo)
  );

  //cache rewrite wb
  wb_simulator #(
    .MEM_FILE("instruction_memory.memh"),
    .DEPTH(1024),
    .LATENCY(3)
  ) wb0 (
    .clk(clk),
    .rst_n(~rst),
    .req(req),
    .we(1'b0),
    .addr(addr_0),
    .wdata(32'd0),
    .rdata(rdata_0),
    .busy(busy_0),
    .valid(valid_0)
    );

  wb_simulator #(
    .MEM_FILE("instruction_memory.memh"),
    .DEPTH(1024),
    .LATENCY(3)
  ) wb1 (
    .clk(clk),
    .rst_n(~rst),
    .req(req),
    .we(1'b0),
    .addr(addr_1),
    .wdata(32'd0),
    .rdata(rdata_1),
    .busy(busy_1),
    .valid(valid_1)
  );

  wb_simulator #(
    .MEM_FILE("instruction_memory.memh"),
    .DEPTH(1024),
    .LATENCY(3)
  ) wb2 (
    .clk(clk),
    .rst_n(~rst),
    .req(req),
    .we(1'b0),
    .addr(addr_2),
    .wdata(32'd0),
    .rdata(rdata_2),
    .busy(busy_2),
    .valid(valid_2)
  );

  wb_simulator #(
    .MEM_FILE("instruction_memory.memh"),
    .DEPTH(1024),
    .LATENCY(3)
  ) wb3 (
    .clk(clk),
    .rst_n(~rst),
    .req(req),
    .we(1'b0),
    .addr(addr_3),
    .wdata(32'd0),
    .rdata(rdata_3),
    .busy(busy_3),
    .valid(valid_3)
  );

endmodule

src/fetch.sv
module fetch (
  input logic clk, rst,

  //cache signals
  input logic cache_ack,
  input logic [31:0] inst,
  output logic addr_ready,
  output logic [31:0] addr,

  //hazard signals
  input logic stall, jal, branch,
  input logic [31:0] j_target, b_target,

  //to decode
  output logic [31:0] final_pc,
  output logic [31:0] final_inst
);

  //stalls are from lw being fetched while instruction behind in EX needs lw regD, can be multiple cycles

  typedef enum {
    SEND,
    WAIT,
    SEND_O,
    WAIT_ACK,
    WAIT_O
  } state_t;

  state_t next_state, state;
  logic [31:0] next_pc, pc;
  logic [31:0] next_finalI, finalI;
  logic [31:0] nop;
  logic [31:0] next_target, target;

  assign nop = 32'h00000013;
  assign final_inst = finalI;
  assign final_pc = pc;

  always_comb begin
    next_state = state;
    addr_ready = 1'b0;
    next_pc = pc;
    next_finalI = nop;
    next_target = target;
    addr = '0;

    case (state) 

      //send cache requests and latch outputs if hit (one cycle state)
      SEND: begin
        if (jal) begin //jal has prio over everything
          addr = j_target;
          addr_ready = 1'b1;
          next_target = j_target;
        end else if (branch) begin //branch and stall can never be at the same time, 
          addr = b_target;
          addr_ready = 1'b1;
          next_target = b_target;
        end else if (!stall) begin //if stall, no instr requested from cache
          addr = pc + 4;
          addr_ready = 1'b1;
        end

        //make hits 1 cycle, remove some of this
        //if stall, then cache_ack will never go high since no request
        if (cache_ack && jal) begin //jal hit
          next_pc = j_target;
          next_finalI = inst;
        end else if (cache_ack && branch) begin //branch hit
          next_pc = b_target;
          next_finalI = inst;
        end else if (cache_ack) begin //PC + 4 hit
          next_pc = pc + 4;
          next_finalI = inst;
        end else if (stall && !jal) begin //if stall, no cache requests, repeat SEND state
          next_pc = pc;
        end else if (jal | branch) begin //jal/branch misses
          next_state = WAIT_O;
        end else begin //normal misses
          next_state = WAIT;
        end
      end

      //normal miss state, jal and branch override the instruction getting fetched. While waiting noop and same PC are latched for decode stage
      WAIT: begin
        if (jal) begin //latch both during their cycle, can't immediately use since I need to wait for cache to finish fetching
          next_target = j_target;
        end else if (branch) begin
          next_target = b_target;
        end

        if (cache_ack && (jal | branch)) begin //ignore cache values, start new cache request with jal/branch
          next_state = SEND_O;
        end else if (cache_ack && stall) begin //current is nop, stall cancels cache miss retrieval time
          next_pc = pc + 4;
          next_finalI = inst;
          next_state = SEND;
        end else if (jal | branch) begin //jal or branch while cache fetching
          next_state = WAIT_ACK; //wait for cache to finish, ignore that value and start new cache request with jal/branch
        end else if (cache_ack) begin
          next_state = SEND;
          next_finalI = inst;
          next_pc = pc + 4;
        end 
        //else case is if no cache_ack, stall can be whatever. if stall high while cache is retrieving, natural stall behavior inst = nop, pc same
      end

      //ignore all hazards, get jal and branch instructions (from latched targets) as they have priority
      SEND_O: begin
        addr_ready = 1'b1;
        addr = target;

        //make hits 1 cycle, so remove
        if (cache_ack) begin
          next_finalI = inst;
          next_pc = target;
          next_state = SEND;
        end else begin
          next_state = WAIT_O; //waits only for cache data, has prio over any hazard signals
        end
      end

      //set instr to nop, pc same while waiting
      WAIT_O: begin
        if (cache_ack) begin
          next_finalI = inst;
          next_pc = target;
          next_state = SEND;
        end
      end

      //wait for cache to sent stale instruction, switch to sending jal/branch addr
      WAIT_ACK: begin
        if (cache_ack) begin
          next_state = SEND_O;
        end
      end
    endcase
  end

  always_ff @(posedge clk or posedge rst) begin
    if (rst) begin
      state <= SEND;
      pc <= -4;
      finalI <= nop;
      target <= '0;
    end else begin
      state <= next_state;
      pc <= next_pc;
      finalI <= next_finalI;
      target <= next_target;
    end
  end
endmodule

tb/tb_fetch.sv
`timescale 1ns/1ps
module tb_fetch;

  logic clk, rst;

  //cache (not driving)
  logic cache_ack, addr_ready;
  logic [31:0] inst, addr;

  //hazard (driving)
  logic stall, jal, branch;
  logic [31:0] j_target, b_target;

  //to decode (monitor)
  logic [31:0] final_inst, final_pc;

  fetch dut (
    .clk(clk),
    .rst(rst),

    //cache signals
    .cache_ack(cache_ack),
    .inst(inst),
    .addr_ready(addr_ready),
    .addr(addr),

    //hazard
    .stall(stall),
    .jal(jal),
    .branch(branch),
    .j_target(j_target),
    .b_target(b_target),

    //to decode
    .final_pc(final_pc),
    .final_inst(final_inst)
  );

  icache i0 (
    .addr(addr),
    .send_pulse(addr_ready),
    .clk(clk),
    .rst(rst),
    .inst(inst),
    .ack(cache_ack)
  );

  initial clk = 0;
  always #10 clk = ~clk;

  task reset();
    rst = 1;
    stall = 0;
    jal = 0;
    branch = 0;
    j_target = '0;
    b_target = '0;
    @(posedge clk);
    @(posedge clk);
    rst = 0;
  endtask

  //nop = 0x13

  task trans (
    //input logic jflush, bflush, stall, js, jb, jmiss, bmiss, smiss,
    //input logic [31:0] jtarg, btarg
  );
    do begin
      @(posedge clk);
    end while (final_inst == 32'h00000013);
    if (final_inst != final_pc) begin
      $display("[%0t] WRONG INST: pc=0x%08h inst=0x%08h", $time, final_pc, final_inst);
    end else begin
      $display("[%0t] CORRECT INST: pc=0x%08h inst=0x%08h", $time, final_pc, final_inst);
    end
  endtask

  initial begin
    $dumpfile("waves.vcd");
    $dumpvars(0, tb_fetch);
    reset();
    //====== test cases
    //normal behavior hit/miss
    //jal flush normal/during a miss
    //branch flush normal/during a miss
    //stall normal/during a miss
    //jal + stall
    //jal + branch
    repeat (10) trans();

    #20;
    $finish;
  end
endmodule

waves.vcd
$date
	Thu Nov 27 20:57:07 2025
$end
$version
	Icarus Verilog
$end
$timescale
	1ps
$end
$scope module tb_fetch $end
$var wire 32 ! inst [31:0] $end
$var wire 32 " final_pc [31:0] $end
$var wire 32 # final_inst [31:0] $end
$var wire 1 $ cache_ack $end
$var wire 1 % addr_ready $end
$var wire 32 & addr [31:0] $end
$var reg 32 ' b_target [31:0] $end
$var reg 1 ( branch $end
$var reg 1 ) clk $end
$var reg 32 * j_target [31:0] $end
$var reg 1 + jal $end
$var reg 1 , rst $end
$var reg 1 - stall $end
$scope module dut $end
$var wire 32 . b_target [31:0] $end
$var wire 1 ( branch $end
$var wire 1 ) clk $end
$var wire 32 / final_inst [31:0] $end
$var wire 32 0 final_pc [31:0] $end
$var wire 32 1 j_target [31:0] $end
$var wire 1 + jal $end
$var wire 32 2 nop [31:0] $end
$var wire 1 , rst $end
$var wire 1 - stall $end
$var wire 32 3 inst [31:0] $end
$var wire 1 $ cache_ack $end
$var reg 32 4 addr [31:0] $end
$var reg 1 % addr_ready $end
$var reg 32 5 finalI [31:0] $end
$var reg 32 6 next_finalI [31:0] $end
$var reg 32 7 next_pc [31:0] $end
$var reg 32 8 next_target [31:0] $end
$var reg 32 9 pc [31:0] $end
$var reg 32 : target [31:0] $end
$var integer 32 ; next_state [31:0] $end
$var integer 32 < state [31:0] $end
$upscope $end
$scope module i0 $end
$var wire 1 $ ack $end
$var wire 32 = addr [31:0] $end
$var wire 1 ) clk $end
$var wire 1 , rst $end
$var wire 1 % send_pulse $end
$var wire 1 > valid_solo $end
$var wire 1 ? valid_3 $end
$var wire 1 @ valid_2 $end
$var wire 1 A valid_1 $end
$var wire 1 B valid_0 $end
$var wire 26 C tag [25:0] $end
$var wire 32 D rdata_solo [31:0] $end
$var wire 32 E rdata_3 [31:0] $end
$var wire 32 F rdata_2 [31:0] $end
$var wire 32 G rdata_1 [31:0] $end
$var wire 32 H rdata_0 [31:0] $end
$var wire 4 I idx [3:0] $end
$var wire 1 J busy_3 $end
$var wire 1 K busy_2 $end
$var wire 1 L busy_1 $end
$var wire 1 M busy_0 $end
$var reg 1 N ack_hit $end
$var reg 1 O ack_miss $end
$var reg 32 P addr_0 [31:0] $end
$var reg 32 Q addr_1 [31:0] $end
$var reg 32 R addr_2 [31:0] $end
$var reg 32 S addr_3 [31:0] $end
$var reg 2 T ct [1:0] $end
$var reg 32 U inst [31:0] $end
$var reg 2 V next_ct [1:0] $end
$var reg 4 W next_idx [3:0] $end
$var reg 26 X next_origin [25:0] $end
$var reg 26 Y origin [25:0] $end
$var reg 4 Z reg_idx [3:0] $end
$var reg 1 [ req $end
$var reg 1 \ req_solo $end
$var integer 32 ] hit [31:0] $end
$var integer 32 ^ next_hit [31:0] $end
$var integer 32 _ next_wb [31:0] $end
$var integer 32 ` next_write [31:0] $end
$var integer 32 a wb [31:0] $end
$var integer 32 b write [31:0] $end
$scope module wb0 $end
$var wire 32 c addr [31:0] $end
$var wire 1 ) clk $end
$var wire 1 [ req $end
$var wire 1 d rst_n $end
$var wire 32 e wdata [31:0] $end
$var wire 1 f we $end
$var parameter 32 g DEPTH $end
$var parameter 32 h LATENCY $end
$var parameter 184 i MEM_FILE $end
$var reg 32 j addr_reg [31:0] $end
$var reg 1 M busy $end
$var reg 2 k counter [1:0] $end
$var reg 1 l pending $end
$var reg 32 m rdata [31:0] $end
$var reg 1 B valid $end
$upscope $end
$scope module wb1 $end
$var wire 32 n addr [31:0] $end
$var wire 1 ) clk $end
$var wire 1 [ req $end
$var wire 1 o rst_n $end
$var wire 32 p wdata [31:0] $end
$var wire 1 q we $end
$var parameter 32 r DEPTH $end
$var parameter 32 s LATENCY $end
$var parameter 184 t MEM_FILE $end
$var reg 32 u addr_reg [31:0] $end
$var reg 1 L busy $end
$var reg 2 v counter [1:0] $end
$var reg 1 w pending $end
$var reg 32 x rdata [31:0] $end
$var reg 1 A valid $end
$upscope $end
$scope module wb2 $end
$var wire 32 y addr [31:0] $end
$var wire 1 ) clk $end
$var wire 1 [ req $end
$var wire 1 z rst_n $end
$var wire 32 { wdata [31:0] $end
$var wire 1 | we $end
$var parameter 32 } DEPTH $end
$var parameter 32 ~ LATENCY $end
$var parameter 184 !" MEM_FILE $end
$var reg 32 "" addr_reg [31:0] $end
$var reg 1 K busy $end
$var reg 2 #" counter [1:0] $end
$var reg 1 $" pending $end
$var reg 32 %" rdata [31:0] $end
$var reg 1 @ valid $end
$upscope $end
$scope module wb3 $end
$var wire 32 &" addr [31:0] $end
$var wire 1 ) clk $end
$var wire 1 [ req $end
$var wire 1 '" rst_n $end
$var wire 32 (" wdata [31:0] $end
$var wire 1 )" we $end
$var parameter 32 *" DEPTH $end
$var parameter 32 +" LATENCY $end
$var parameter 184 ," MEM_FILE $end
$var reg 32 -" addr_reg [31:0] $end
$var reg 1 J busy $end
$var reg 2 ." counter [1:0] $end
$var reg 1 /" pending $end
$var reg 32 0" rdata [31:0] $end
$var reg 1 ? valid $end
$upscope $end
$scope module wb_solo_inst $end
$var wire 32 1" addr [31:0] $end
$var wire 1 ) clk $end
$var wire 1 \ req $end
$var wire 1 2" rst_n $end
$var wire 32 3" wdata [31:0] $end
$var wire 1 4" we $end
$var parameter 32 5" DEPTH $end
$var parameter 32 6" LATENCY $end
$var parameter 184 7" MEM_FILE $end
$var reg 32 8" addr_reg [31:0] $end
$var reg 1 9" busy $end
$var reg 2 :" counter [1:0] $end
$var reg 1 ;" pending $end
$var reg 32 <" rdata [31:0] $end
$var reg 1 > valid $end
$upscope $end
$upscope $end
$scope task reset $end
$upscope $end
$scope task trans $end
$upscope $end
$upscope $end
$enddefinitions $end
$comment Show the parameter values. $end
$dumpall
b110100101101110011100110111010001110010011101010110001101110100011010010110111101101110010111110110110101100101011011010110111101110010011110010010111001101101011001010110110101101000 7"
b11 6"
b10000000000 5"
b110100101101110011100110111010001110010011101010110001101110100011010010110111101101110010111110110110101100101011011010110111101110010011110010010111001101101011001010110110101101000 ,"
b11 +"
b10000000000 *"
b110100101101110011100110111010001110010011101010110001101110100011010010110111101101110010111110110110101100101011011010110111101110010011110010010111001101101011001010110110101101000 !"
b11 ~
b10000000000 }
b110100101101110011100110111010001110010011101010110001101110100011010010110111101101110010111110110110101100101011011010110111101110010011110010010111001101101011001010110110101101000 t
b11 s
b10000000000 r
b110100101101110011100110111010001110010011101010110001101110100011010010110111101101110010111110110110101100101011011010110111101110010011110010010111001101101011001010110110101101000 i
b11 h
b10000000000 g
$end
#0
$dumpvars
b0 <"
0;"
b0 :"
09"
bx 8"
04"
b0 3"
02"
b0 1"
b0 0"
0/"
b0 ."
bx -"
0)"
b0 ("
0'"
b0 &"
b0 %"
0$"
b0 #"
bx ""
0|
b0 {
0z
b0 y
b0 x
0w
b0 v
bx u
0q
b0 p
0o
b0 n
b0 m
0l
b0 k
bx j
0f
b0 e
0d
b0 c
b11 b
b10 a
b0 `
b0 _
b0 ^
b0 ]
0\
0[
b0 Z
b0 Y
b0 X
b0 W
b0 V
b0 U
b0 T
b0 S
b0 R
b0 Q
b0 P
0O
0N
0M
0L
0K
0J
b0 I
b0 H
b0 G
b0 F
b0 E
b0 D
b0 C
0B
0A
0@
0?
0>
b0 =
b0 <
b1 ;
b0 :
b11111111111111111111111111111100 9
b0 8
b11111111111111111111111111111100 7
b10011 6
b10011 5
b0 4
b0 3
b10011 2
b0 1
b11111111111111111111111111111100 0
b10011 /
b0 .
0-
1,
0+
b0 *
0)
0(
b0 '
b0 &
1%
0$
b10011 #
b11111111111111111111111111111100 "
b0 !
$end
#10000
1)
#20000
0)
#30000
0%
b10 `
b1100 S
b1100 &"
b1000 R
b1000 y
b100 Q
b100 n
1[
b1 _
1\
b1 <
b0 a
b0 b
12"
1d
1o
1z
1'"
0,
1)
#40000
0)
#50000
b0 S
b0 &"
b0 R
b0 y
b0 Q
b0 n
0[
0\
b1 a
b10 b
b0 j
b10 k
1M
1l
b100 u
b10 v
1L
1w
b1000 ""
b10 #"
1K
1$"
b1100 -"
b10 ."
1J
1/"
b0 8"
b10 :"
19"
1;"
1)
#60000
0)
#70000
b1 k
b1 v
b1 #"
b1 ."
b1 :"
1)
#80000
0)
#90000
b0 k
b0 v
b0 #"
b0 ."
b0 :"
1)
#100000
0)
#110000
b0 7
b0 6
b0 ;
1$
b1 V
b0 `
1O
b10 _
1B
0M
0l
1A
b100 G
b100 x
0L
0w
1@
b1000 F
b1000 %"
0K
0$"
1?
b1100 E
b1100 0"
0J
0/"
1>
09"
0;"
1)
#120000
0)
#130000
b1 ;
b1 ^
b1 W
b1 I
0$
b0 7
1%
b100 &
b100 4
b100 =
b100 1"
b10011 6
b11100 S
b11100 &"
b11000 R
b11000 y
b10100 Q
b10100 n
b10000 P
b10000 c
1[
b1 T
b10 a
b0 b
b0 #
b0 /
b0 5
b0 "
b0 0
b0 9
b0 <
0B
0A
0@
0?
0>
b10 `
b1 V
b10 _
0O
1)
#140000
0)
#150000
b0 W
b100 7
b100 6
b0 ;
b0 I
1$
b0 &
b0 4
b0 =
b0 1"
0%
1N
b100 !
b100 3
b100 U
b0 ^
b0 S
b0 &"
b0 R
b0 y
b0 Q
b0 n
b0 P
b0 c
0[
b10011 #
b10011 /
b10011 5
b1 <
b10 b
b1 ]
b1 Z
b10000 j
b10 k
1M
1l
b10100 u
b10 v
1L
1w
b11000 ""
b10 #"
1K
1$"
b11100 -"
b10 ."
1J
1/"
1)
#160000
0)
#170000
b10 W
b1 ;
0$
b10 I
b1 ^
b0 !
b0 3
b0 U
0N
b100 7
1%
b1000 &
b1000 4
b1000 =
b1000 1"
b10011 6
b0 ]
b0 Z
b100 #
b100 /
b100 5
b100 "
b100 0
b100 9
b0 <
b1 k
b1 v
b1 #"
b1 ."
1)
#180000
0)
#190000
b0 W
b1000 7
b1000 6
b0 ;
b0 I
1$
b0 &
b0 4
b0 =
b0 1"
0%
1N
b1000 !
b1000 3
b1000 U
b0 ^
b10011 #
b10011 /
b10011 5
b1 <
b1 ]
b10 Z
b0 k
b0 v
b0 #"
b0 ."
1)
#200000
0)
#210000
b1 ;
b1 ^
b11 W
b11 I
0$
b1000 7
1%
b1100 &
b1100 4
b1100 =
b1100 1"
b10011 6
b10 V
b0 `
b0 !
b0 3
b0 U
0N
b0 ]
b0 Z
b1000 #
b1000 /
b1000 5
b1000 "
b1000 0
b1000 9
b0 <
1B
b10000 H
b10000 m
0M
0l
1A
b10100 G
b10100 x
0L
0w
1@
b11000 F
b11000 %"
0K
0$"
1?
b11100 E
b11100 0"
0J
0/"
1)
#220000
0)
#230000
b0 W
b1100 7
b1100 6
b0 ;
b0 I
1$
b0 &
b0 4
b0 =
b0 1"
0%
b101100 S
b101100 &"
b101000 R
b101000 y
b100100 Q
b100100 n
b100000 P
b100000 c
1[
1N
b1100 !
b1100 3
b1100 U
b10011 #
b10011 /
b10011 5
b1 <
b10 T
b0 b
b1 ]
b11 Z
0B
0A
0@
0?
b0 ^
b10 `
b10 V
1)
#240000
0)
#250000
b1 ;
b1 ^
b100 W
b100 I
0$
b1100 7
1%
b10000 &
b10000 4
b10000 =
b10000 1"
b10011 6
b0 S
b0 &"
b0 R
b0 y
b0 Q
b0 n
b0 P
b0 c
0[
b0 !
b0 3
b0 U
0N
b10 b
b0 ]
b0 Z
b1100 #
b1100 /
b1100 5
b1100 "
b1100 0
b1100 9
b0 <
b100000 j
b10 k
1M
1l
b100100 u
b10 v
1L
1w
b101000 ""
b10 #"
1K
1$"
b101100 -"
b10 ."
1J
1/"
1)
#260000
0)
#270000
b0 W
b10000 7
b10000 6
b0 ;
b0 I
1$
b0 &
b0 4
b0 =
b0 1"
0%
1N
b10000 !
b10000 3
b10000 U
b0 ^
b10011 #
b10011 /
b10011 5
b1 <
b1 ]
b100 Z
b1 k
b1 v
b1 #"
b1 ."
1)
#280000
0)
#290000
b101 W
b1 ;
0$
b101 I
b1 ^
b0 !
b0 3
b0 U
0N
b10000 7
1%
b10100 &
b10100 4
b10100 =
b10100 1"
b10011 6
b0 ]
b0 Z
b10000 #
b10000 /
b10000 5
b10000 "
b10000 0
b10000 9
b0 <
b0 k
b0 v
b0 #"
b0 ."
1)
#300000
0)
#310000
b0 W
b10100 7
b10100 6
b0 ;
b0 I
1$
b0 &
b0 4
b0 =
b0 1"
0%
b11 V
b0 `
1N
b10100 !
b10100 3
b10100 U
b0 ^
b10011 #
b10011 /
b10011 5
b1 <
b1 ]
b101 Z
1B
b100000 H
b100000 m
0M
0l
1A
b100100 G
b100100 x
0L
0w
1@
b101000 F
b101000 %"
0K
0$"
1?
b101100 E
b101100 0"
0J
0/"
1)
#320000
0)
#330000
b110 W
b110 I
0$
1%
b11000 &
b11000 4
b11000 =
b11000 1"
b111100 S
b111100 &"
b111000 R
b111000 y
b110100 Q
b110100 n
b110000 P
b110000 c
1[
b11 T
b0 b
b0 ]
b0 Z
b10100 #
b10100 /
b10100 5
b10100 "
b10100 0
b10100 9
b0 <
0B
0A
0@
0?
b10011 6
b10100 7
b1 ;
b1 ^
b10 `
b11 V
b0 !
b0 3
b0 U
0N
1)
#340000
0)
#350000
b0 W
b11000 7
b11000 6
b0 ;
b0 I
1$
b0 &
b0 4
b0 =
b0 1"
0%
1N
b11000 !
b11000 3
b11000 U
b0 ^
b0 S
b0 &"
b0 R
b0 y
b0 Q
b0 n
b0 P
b0 c
0[
b10011 #
b10011 /
b10011 5
b1 <
b10 b
b1 ]
b110 Z
b110000 j
b10 k
1M
1l
b110100 u
b10 v
1L
1w
b111000 ""
b10 #"
1K
1$"
b111100 -"
b10 ."
1J
1/"
1)
#360000
0)
#370000
b111 W
b1 ;
0$
b111 I
b1 ^
b0 !
b0 3
b0 U
0N
b11000 7
1%
b11100 &
b11100 4
b11100 =
b11100 1"
b10011 6
b0 ]
b0 Z
b11000 #
b11000 /
b11000 5
b11000 "
b11000 0
b11000 9
b0 <
b1 k
b1 v
b1 #"
b1 ."
1)
#380000
0)
#390000
b0 W
b11100 7
b11100 6
b0 ;
b0 I
1$
b0 &
b0 4
b0 =
b0 1"
0%
1N
b11100 !
b11100 3
b11100 U
b0 ^
b10011 #
b10011 /
b10011 5
b1 <
b1 ]
b111 Z
b0 k
b0 v
b0 #"
b0 ."
1)
#400000
0)
#410000
b1 ;
b1 ^
b1000 W
b1000 I
0$
b11100 7
1%
b100000 &
b100000 4
b100000 =
b100000 1"
b10011 6
b0 V
b11 `
b0 !
b0 3
b0 U
0N
b0 ]
b0 Z
b11100 #
b11100 /
b11100 5
b11100 "
b11100 0
b11100 9
b0 <
1B
b110000 H
b110000 m
0M
0l
1A
b110100 G
b110100 x
0L
0w
1@
b111000 F
b111000 %"
0K
0$"
1?
b111100 E
b111100 0"
0J
0/"
1)
#420000
0)
#430000
b0 W
b100000 7
b100000 6
b0 ;
b0 I
1$
b0 &
b0 4
b0 =
b0 1"
0%
1N
b100000 !
b100000 3
b100000 U
b10011 #
b10011 /
b10011 5
b1 <
b0 T
b11 b
b1 ]
b1000 Z
0B
0A
0@
0?
b0 ^
b11 `
b0 V
1)
#440000
0)
#450000
b1001 W
b1 ;
0$
b1001 I
b1 ^
b0 !
b0 3
b0 U
0N
b100000 7
1%
b100100 &
b100100 4
b100100 =
b100100 1"
b10011 6
b0 ]
b0 Z
b100000 #
b100000 /
b100000 5
b100000 "
b100000 0
b100000 9
b0 <
1)
#460000
0)
#470000
b0 W
b100100 7
b100100 6
b0 ;
b0 I
1$
b0 &
b0 4
b0 =
b0 1"
0%
1N
b100100 !
b100100 3
b100100 U
b0 ^
b10011 #
b10011 /
b10011 5
b1 <
b1 ]
b1001 Z
1)
#480000
0)
#490000
b1010 W
b1 ;
0$
b1010 I
b1 ^
b0 !
b0 3
b0 U
0N
b100100 7
1%
b101000 &
b101000 4
b101000 =
b101000 1"
b10011 6
b0 ]
b0 Z
b100100 #
b100100 /
b100100 5
b100100 "
b100100 0
b100100 9
b0 <
1)
#500000
0)
