src/decode.sv
module decode (
  input logic clk, rst,

  //hazard
  input logic stall, jal_flush, branch_flush,

  //fetch
  input logic [31:0] inst, pc,

  //regfile
  input logic [31:0] file_val1, file_val2,
  output logic [4:0] file_reg1, file_reg2,

  //output to execute
  output logic rtype, itype, load, store, branch, jal, jalr, //itype flag is for opcode 0010011
  output logic [31:0] imm, finalI, finalpc,
  output logic [4:0] reg1, reg2, regD,
  output logic [31:0] reg1val, reg2val
);

  //supports rtype, itype, branching, jal, jalr, lw (full word), sw (full word), NO UTYPE OR ENVIRONMENT

  //internal signals
  logic next_rtype, next_itype, next_load, next_store, next_branch, next_jal, next_jalr;
  logic [31:0] next_imm, next_finalI, next_finalpc;
  logic [4:0] next_reg1, next_reg2, next_regD;
  //logic [31:0] next_reg1val, next_reg2val;
  logic [6:0] op;
  logic [31:0] nop;

  assign op = inst[6:0];
  assign nop = 32'h00000013;

  always_comb begin
    //default nop
    next_itype = 0;
    next_rtype = 0;
    next_load = 0;
    next_store = 0;
    next_branch = 0;
    next_jal = 0;
    next_jalr = 0;
    next_imm = '0;
    next_reg1 = '0;
    next_reg2 = '0;
    next_regD = '0;
    //next_reg1val = '0;
    //next_reg2val = '0;
    next_finalI = inst;
    next_finalpc = pc;
    file_reg1 = '0;
    file_reg2 = '0;

    //jal and branch flush, so defaults are valid
    if (jal_flush || branch_flush) begin
      next_finalI = nop;
      next_itype = 1;
    end else if (stall) begin
      next_itype = itype;
      next_rtype = rtype;
      next_load = load;
      next_store = store;
      next_branch = branch;
      next_jal = jal;
      next_jalr = jalr;
      next_imm = imm;
      next_reg1 = reg1;
      next_reg2 = reg2;
      next_regD = regD;
      //next_reg1val = reg1val;
      //next_reg2val = reg2val;
      next_finalI = finalI;
      next_finalpc = finalpc;
      file_reg1 = reg1;
      file_reg2 = reg2;
    end else begin
      //fill next type, imm, reg based on opcodes
      case (op)
        7'b0110011: begin //rtype: reg1, reg2, regD
          next_rtype = 1;
          next_reg1 = inst[19:15];
          next_reg2 = inst[24:20];
          next_regD = inst[11:7];
          //register file fetch
          file_reg1 = next_reg1;
          file_reg2 = next_reg2;
          //=== COMB
          //next_reg1val = file_val1; 
          //next_reg2val = file_val2;
        end
        7'b0010011: begin //itype: imm, reg1, regD
          next_itype = 1;
          next_reg1 = inst [19:15];
          next_regD = inst [11:7];
          next_imm = {{20{inst[31]}}, inst[31:20]};
          //register file fetch
          file_reg1 = next_reg1;
          //== COMB
          //next_reg1val = file_val1;
        end
        7'b0000011: begin //load: imm, reg1, regD
          next_load = 1;
          next_reg1 = inst [19:15];
          next_regD = inst [11:7];
          next_imm = {{20{inst[31]}}, inst[31:20]};
          //register file fetch
          file_reg1 = next_reg1;
          //== COMB
          //next_reg1val = file_val1;
        end
        7'b0100011: begin //store: reg1, reg2, imm
          next_store = 1;
          next_reg1 = inst [19:15];
          next_reg2 = inst [24:20];
          next_imm = {{20{inst[31]}}, inst[31:25], inst[11:7]};
          //register file fetch
          file_reg1 = next_reg1;
          file_reg2 = next_reg2;
          //== COMB
          //next_reg1val = file_val1;
          //next_reg2val = file_val2;
        end
        7'b1100011: begin //branch: reg1, reg2, imm
          next_branch = 1;
          next_reg1 = inst[19:15];
          next_reg2 = inst[24:20];
          next_imm = {{19{inst[31]}}, inst[31], inst[7], inst[30:25], inst[11:8], 1'b0};
          //register file fetch
          file_reg1 = next_reg1;
          file_reg2 = next_reg2;
          // == COMB
          //next_reg1val = file_val1;
          //next_reg2val = file_val2;
        end
        7'b1101111: begin //jal: imm, regD
          next_jal = 1;
          next_imm = {{11{inst[31]}}, inst[31], inst[19:12], inst[20], inst[30:21], 1'b0};
          next_regD = inst [11:7];
        end
        7'b1100111: begin //jalr: imm, reg1, regD
          next_jalr = 1;
          next_reg1 = inst [19:15];
          next_regD = inst [11:7];
          next_imm = {{20{inst[31]}}, inst[31:20]};
          //register file fetch
          file_reg1 = next_reg1;
          // == COMB
          //next_reg1val = file_val1;
        end
      endcase
    end
  end

  always_ff @(posedge clk or posedge rst) begin
    if (rst) begin
      itype <= 1;
      rtype <= 0;
      load <= 0;
      store <= 0;
      branch <= 0;
      jal <= 0;
      jalr <= 0;
      imm <= '0;
      reg1 <= '0;
      reg2 <= '0;
      regD <= '0;
      reg1val <= '0;
      reg2val <= '0;
      finalI <= nop;
      finalpc <= '0;
    end else begin
      itype <= next_itype;
      rtype <= next_rtype;
      load <= next_load;
      store <= next_store;
      branch <= next_branch;
      jal <= next_jal;
      jalr <= next_jalr;
      imm <= next_imm;
      reg1 <= next_reg1;
      reg2 <= next_reg2;
      regD <= next_regD;
      reg1val <= file_val1;
      reg2val <= file_val2;
      finalI <= next_finalI;
      finalpc <= next_finalpc;
    end
  end
endmodule

tb/tb_decode.sv
`timescale 1ns/1ps
module tb_decode;

  logic clk, rst;

  //regfile
  logic [31:0] file_val1, file_val2;
  logic [4:0] file_reg1, file_reg2;

  //dut
  logic stall, jal_flush, branch_flush, rtype, itype;
  logic load, store, branch, jal, jalr;
  logic [31:0] inst, pc, imm, finalI, finalpc;
  logic [4:0] reg1, reg2, regD;
  logic [31:0] reg1val, reg2val;

  decode dut (
    .clk(clk),
    .rst(rst),

    //hazards (drive)
    .stall(stall),
    .jal_flush(jal_flush),
    .branch_flush(branch_flush),

    //from fetch (drive)
    .inst(inst),
    .pc(pc),

    //regfile inputs (drive)
    .file_val1(file_val1),
    .file_val2(file_val2),

    //regfile outputs (monitor)
    .file_reg1(file_reg1),
    .file_reg2(file_reg2),

    //to execute (monitor)
    .rtype(rtype),
    .itype(itype),
    .load(load),
    .store(store),
    .branch(branch),
    .jal(jal),
    .jalr(jalr),
    .imm(imm),
    .finalI(finalI),
    .finalpc(finalpc),
    .reg1(reg1),
    .reg2(reg2),
    .regD(regD),
    .reg1val(reg1val),
    .reg2val(reg2val)
  );

  //tasks for all instructions that take hazard flags

  initial clk = 0;
  always #10 clk = ~clk;

  task reset();
    rst = 1;
    stall = 0;
    jal_flush = 0;
    branch_flush = 0;
    file_val1 = '0;
    file_val2 = '0;
    inst = '0;
    pc = '0;
    @(posedge clk);
    @(posedge clk);
    rst = 0;
  endtask

  task send (
    input logic [31:0] inst_send, pc_send,
    input logic rt, it, lo, st, br, ja, jr,
    input logic j, b, s 
  );
    logic [4:0] reg1_exp, reg2_exp, regD_exp;
    logic [31:0] imm_exp, file_val1_exp, file_val2_exp;

    //stall val
    logic [4:0] prev_reg1, prev_reg2, prev_regD;
    logic [31:0] prev_imm, prev_file_val1, prev_file_val2, prev_finalI, prev_finalpc;
    logic prev_rt, prev_it, prev_lo, prev_st, prev_br, prev_ja, prev_jr;
    
    reg1_exp = '0;
    reg2_exp = '0;
    regD_exp = '0;
    imm_exp = '0;
    file_val1_exp = '0;
    file_val2_exp = '0;

    //im always driving regfile val as aa, bb

    //=== output predictor
    if (rt) begin
      reg1_exp = inst_send[19:15];
      reg2_exp = inst_send[24:20];
      regD_exp = inst_send[11:7];
    end else if (it || lo || jr) begin
      reg1_exp = inst_send [19:15];
      regD_exp = inst_send [11:7];
      imm_exp = {{20{inst_send[31]}}, inst_send[31:20]};
    end else if (st) begin
      reg1_exp = inst_send[19:15];
      reg2_exp = inst_send[24:20];
      imm_exp = {{20{inst_send[31]}}, inst_send[31:25], inst_send[11:7]};
    end else if (br) begin
      reg1_exp = inst_send[19:15];
      reg2_exp = inst_send[24:20];
      imm_exp = {{19{inst_send[31]}}, inst_send[31], inst_send[7], inst_send[30:25], inst_send[11:8], 1'b0};
    end else if (ja) begin
      regD_exp = inst_send[11:7];
      imm_exp = {{11{inst_send[31]}}, inst_send[31], inst_send[19:12], inst_send[20], inst_send[30:21], 1'b0};
    end else $display("ERROR: NO INSTRUCTION FLAG RAISED FOR THIS TASK");
    #0;
    prev_reg1 = reg1;
    prev_reg2 = reg2;
    prev_regD = regD;
    prev_imm = imm;
    prev_file_val1 = reg1val;
    prev_file_val2 = reg2val;
    prev_finalI = finalI;
    prev_finalpc = finalpc;
    prev_rt = rtype;
    prev_it = itype;
    prev_lo = load;
    prev_st = store;
    prev_br = branch;
    prev_ja = jal;
    prev_jr = jalr;

    #0;
    jal_flush = j;
    branch_flush = b;
    stall = s;
    inst = inst_send;
    pc = pc_send;
    #0;

    //check reg req to regfile
    if (file_reg1 != reg1_exp && !j && !b && !s) begin
      $display("Reg1 mismatch: Sent to reg file: 0x%8h Expected: 0x%8h", file_reg1, reg1_exp);
    end 
    if (file_reg2 != reg2_exp && !j && !b && !s) begin
      $display("Reg2 mismatch: Sent to reg file: 0x%8h Expected: 0x%8h", file_reg2, reg2_exp);
    end

    //drive regfile inputs
    #0;
    if (file_reg1 != '0) file_val1_exp = 32'hAA;
    if (file_reg2 != '0) file_val2_exp = 32'hBB;
    file_val1 = file_val1_exp;
    file_val2 = file_val2_exp;

    @(posedge clk); //values are now registered
    #2;
    if (j || b) begin
      if (finalI == 32'h13 
          && rtype == 0
          && itype == 1
          && load == 0
          && store == 0
          && branch == 0
          && jal == 0
          && jalr == 0
          && imm == '0
          && reg1 == '0
          && reg2 == '0
          && regD == '0
          && reg1val == '0
          && reg2val == '0) begin
         $display("PASS w HAZARD: instr = 0x%8h jal = %d branch = %d", inst_send, j, b);
          end else $display("FAIL w HAZARD: instr = 0x%8h jal = %d branch = %d", inst_send, j, b);
    end else if (s) begin
      if (finalI == prev_finalI 
          && finalpc == prev_finalpc
          && rtype == prev_rt
          && itype == prev_it
          && load == prev_lo
          && store == prev_st
          && branch == prev_br
          && jal == prev_ja
          && jalr == prev_jr
          && imm == prev_imm
          && reg1 == prev_reg1
          && reg2 == prev_reg2
          && regD == prev_regD
          && reg1val == prev_file_val1
          && reg2val == prev_file_val2) begin
         $display("PASS w STALL: instr = 0x%8h finalI = 0x%8h", inst_send, finalI);
         
          end else $display("FAIL w STALL: instr = 0x%8h", inst_send);
    end
    else begin
      if (finalI == inst_send 
          && rtype == rt
          && itype == it
          && load == lo
          && store == st
          && branch == br
          && jal == ja
          && jalr == jr
          && imm == imm_exp
          && reg1 == reg1_exp
          && reg2 == reg2_exp
          && regD == regD_exp
          && reg1val == file_val1_exp
          && reg2val == file_val2_exp) begin
         $display("PASS: instr = 0x%8h", inst_send);
    end else begin 
      $display("FAIL: instr = 0x%8h", inst_send);
      $display("exp rtype: %d actual rtype: %d", rt, rtype);
      $display("exp itype: %d actual itype: %d", it, itype);
      $display("exp load: %d actual load: %d", lo, load);
      $display("exp store: %d actual store: %d", st, store);
      $display("exp branch: %d actual rtype: %d", br, branch);
      $display("exp jal: %d actual jal: %d", ja, jal);
      $display("exp jalr: %d actual jalr: %d", jr, jalr);
      $display("exp imm: %8h actual imm: %8h", imm_exp, imm);
      $display("exp reg1val: %8h actual reg1val: %8h", file_val1_exp, reg1val);
      $display("exp reg2val: %8h actual reg2val: %8h", file_val2_exp, reg2val);
      $display("exp reg1: %d actual reg1: %d", reg1_exp, reg1);
      $display("exp reg2: %d actual reg2: %d", reg2_exp, reg2);
      $display("exp regD: %d actual regD: %d", regD_exp, regD);
    end
    end
  endtask

  initial begin
    $dumpfile("sim/waves.vcd");
    $dumpvars(0, tb_decode);
    reset();

    //==== test cases
    
    //every instruction type without hazards
    send (32'h007302b3, 32'hcc, 1, 0, 0, 0, 0, 0, 0, 0, 0, 0); //add x5, x6, x7
    send (32'h40020633, 32'hcc, 1, 0, 0, 0, 0, 0, 0, 0, 0, 0); //sub x12, x4, x0
    send (32'h00447033, 32'hcc, 1, 0, 0, 0, 0, 0, 0, 0, 0, 0); //and x0, x8, x4
    send (32'h01618413, 32'hcc, 0, 1, 0, 0, 0, 0, 0, 0, 0, 0); //addi x8, x3, 22
    send (32'h0ff2e193, 32'hcc, 0, 1, 0, 0, 0, 0, 0, 0, 0, 0); //ori x3, x5, 0xFF
    send (32'h00449113, 32'hcc, 0, 1, 0, 0, 0, 0, 0, 0, 0, 0); //slli x2, x9, 0x4
    send (32'h00412903, 32'hcc, 0, 0, 1, 0, 0, 0, 0, 0, 0, 0); //lw x18, 4(x2)
    send (32'h00c4a283, 32'hcc, 0, 0, 1, 0, 0, 0, 0, 0, 0, 0); //lw x5, 12(x9)
    send (32'h00002003, 32'hcc, 0, 0, 1, 0, 0, 0, 0, 0, 0, 0); //lw x0, 0(x0)
    send (32'h00312623, 32'hcc, 0, 0, 0, 1, 0, 0, 0, 0, 0, 0); //sw x3, 12(x2)
    send (32'h01c92223, 32'hcc, 0, 0, 0, 1, 0, 0, 0, 0, 0, 0); //sw x28, 4(x18)
    send (32'h01802423, 32'hcc, 0, 0, 0, 1, 0, 0, 0, 0, 0, 0); //sw x24, 8(x0)
    send (32'hfe8104e3, 32'hcc, 0, 0, 0, 0, 1, 0, 0, 0, 0, 0); //beq x2, x8, branch1
    send (32'hfe7016e3, 32'hcc, 0, 0, 0, 0, 1, 0, 0, 0, 0, 0); //bne x0, x7, branch2
    send (32'hfea2cee3, 32'hcc, 0, 0, 0, 0, 1, 0, 0, 0, 0, 0); //blt x5, x10, branch3
    send (32'hfddff46f, 32'hcc, 0, 0, 0, 0, 0, 1, 0, 0, 0, 0); //jal x8, branch1
    send (32'hfe1ff06f, 32'hcc, 0, 0, 0, 0, 0, 1, 0, 0, 0, 0); //jal x0, branch2
    send (32'hff1fff6f, 32'hcc, 0, 0, 0, 0, 0, 1, 0, 0, 0, 0); //jal x30, branch3
    send (32'h00040467, 32'hcc, 0, 0, 0, 0, 0, 0, 1, 0, 0, 0); //jalr x8, 0(x8)
    send (32'h00498267, 32'hcc, 0, 0, 0, 0, 0, 0, 1, 0, 0, 0); //jalr x4, 4(x19)
    send (32'h01060d67, 32'hcc, 0, 0, 0, 0, 0, 0, 1, 0, 0, 0); //jalr x26, 16(x12)

    //every hazard
    send (32'h007302b3, 32'hcc, 1, 0, 0, 0, 0, 0, 0, 1, 0, 0); //add x5, x6, x7
    send (32'h40020633, 32'hcc, 1, 0, 0, 0, 0, 0, 0, 0, 1, 0); //sub x12, x4, x0
    send (32'h00447033, 32'hcc, 1, 0, 0, 0, 0, 0, 0, 0, 0, 1); //and x0, x8, x4
    send (32'h01618413, 32'hcc, 0, 1, 0, 0, 0, 0, 0, 1, 0, 0); //addi x8, x3, 22
    send (32'h0ff2e193, 32'hcc, 0, 1, 0, 0, 0, 0, 0, 0, 1, 0); //ori x3, x5, 0xFF
    send (32'h00449113, 32'hcc, 0, 1, 0, 0, 0, 0, 0, 0, 0, 1); //slli x2, x9, 0x4
    send (32'h00412903, 32'hcc, 0, 0, 1, 0, 0, 0, 0, 1, 0, 0); //lw x18, 4(x2)
    send (32'h00c4a283, 32'hcc, 0, 0, 1, 0, 0, 0, 0, 0, 1, 0); //lw x5, 12(x9)
    send (32'h00002003, 32'hcc, 0, 0, 1, 0, 0, 0, 0, 0, 0, 1); //lw x0, 0(x0)
    send (32'h00312623, 32'hcc, 0, 0, 0, 1, 0, 0, 0, 1, 0, 0); //sw x3, 12(x2)
    send (32'h01c92223, 32'hcc, 0, 0, 0, 1, 0, 0, 0, 0, 1, 0); //sw x28, 4(x18)
    send (32'h01802423, 32'hcc, 0, 0, 0, 1, 0, 0, 0, 0, 0, 1); //sw x24, 8(x0)
    send (32'hfe8104e3, 32'hcc, 0, 0, 0, 0, 1, 0, 0, 1, 0, 0); //beq x2, x8, branch1
    send (32'hfe7016e3, 32'hcc, 0, 0, 0, 0, 1, 0, 0, 0, 1, 0); //bne x0, x7, branch2
    send (32'hfea2cee3, 32'hcc, 0, 0, 0, 0, 1, 0, 0, 0, 0, 1); //blt x5, x10, branch3
    send (32'hfddff46f, 32'hcc, 0, 0, 0, 0, 0, 1, 0, 1, 0, 0); //jal x8, branch1
    send (32'hfe1ff06f, 32'hcc, 0, 0, 0, 0, 0, 1, 0, 0, 1, 0); //jal x0, branch2
    send (32'hff1fff6f, 32'hcc, 0, 0, 0, 0, 0, 1, 0, 0, 0, 1); //jal x30, branch3
    send (32'h00040467, 32'hcc, 0, 0, 0, 0, 0, 0, 1, 1, 0, 0); //jalr x8, 0(x8)
    send (32'h00498267, 32'hcc, 0, 0, 0, 0, 0, 0, 1, 0, 1, 0); //jalr x4, 4(x19)
    send (32'h01060d67, 32'hdd, 0, 0, 0, 0, 0, 0, 1, 0, 0, 1); //jalr x26, 16(x12)

    send (32'h00498267, 32'hcc, 0, 0, 0, 0, 0, 0, 1, 0, 0, 0); //jalr x4, 4(x19)
    send (32'h01060d67, 32'hcc, 0, 0, 0, 0, 0, 0, 1, 0, 0, 0); //jalr x26, 16(x12)
    //multicycle stall
    send (32'h00412903, 32'hAA, 0, 0, 1, 0, 0, 0, 0, 0, 0, 1); //lw x18, 4(x2)
    send (32'hff1fff6f, 32'hbb, 0, 0, 0, 0, 0, 1, 0, 0, 0, 1); //jal x30, branch3
    send (32'h00449113, 32'hcc, 0, 1, 0, 0, 0, 0, 0, 0, 0, 1); //slli x2, x9, 0x4

    #20;
    $finish;
  end
endmodule

sim/waves.vcd
$date
	Mon Dec 01 02:37:21 2025
$end
$version
	Icarus Verilog
$end
$timescale
	1ps
$end
$scope module tb_decode $end
$var wire 1 ! store $end
$var wire 1 " rtype $end
$var wire 5 # regD [4:0] $end
$var wire 32 $ reg2val [31:0] $end
$var wire 5 % reg2 [4:0] $end
$var wire 32 & reg1val [31:0] $end
$var wire 5 ' reg1 [4:0] $end
$var wire 1 ( load $end
$var wire 1 ) jalr $end
$var wire 1 * jal $end
$var wire 1 + itype $end
$var wire 32 , imm [31:0] $end
$var wire 32 - finalpc [31:0] $end
$var wire 32 . finalI [31:0] $end
$var wire 5 / file_reg2 [4:0] $end
$var wire 5 0 file_reg1 [4:0] $end
$var wire 1 1 branch $end
$var reg 1 2 branch_flush $end
$var reg 1 3 clk $end
$var reg 32 4 file_val1 [31:0] $end
$var reg 32 5 file_val2 [31:0] $end
$var reg 32 6 inst [31:0] $end
$var reg 1 7 jal_flush $end
$var reg 32 8 pc [31:0] $end
$var reg 1 9 rst $end
$var reg 1 : stall $end
$scope module dut $end
$var wire 1 2 branch_flush $end
$var wire 1 3 clk $end
$var wire 32 ; file_val1 [31:0] $end
$var wire 32 < file_val2 [31:0] $end
$var wire 32 = inst [31:0] $end
$var wire 1 7 jal_flush $end
$var wire 32 > nop [31:0] $end
$var wire 32 ? pc [31:0] $end
$var wire 1 9 rst $end
$var wire 1 : stall $end
$var wire 7 @ op [6:0] $end
$var reg 1 1 branch $end
$var reg 5 A file_reg1 [4:0] $end
$var reg 5 B file_reg2 [4:0] $end
$var reg 32 C finalI [31:0] $end
$var reg 32 D finalpc [31:0] $end
$var reg 32 E imm [31:0] $end
$var reg 1 + itype $end
$var reg 1 * jal $end
$var reg 1 ) jalr $end
$var reg 1 ( load $end
$var reg 1 F next_branch $end
$var reg 32 G next_finalI [31:0] $end
$var reg 32 H next_finalpc [31:0] $end
$var reg 32 I next_imm [31:0] $end
$var reg 1 J next_itype $end
$var reg 1 K next_jal $end
$var reg 1 L next_jalr $end
$var reg 1 M next_load $end
$var reg 5 N next_reg1 [4:0] $end
$var reg 5 O next_reg2 [4:0] $end
$var reg 5 P next_regD [4:0] $end
$var reg 1 Q next_rtype $end
$var reg 1 R next_store $end
$var reg 5 S reg1 [4:0] $end
$var reg 32 T reg1val [31:0] $end
$var reg 5 U reg2 [4:0] $end
$var reg 32 V reg2val [31:0] $end
$var reg 5 W regD [4:0] $end
$var reg 1 " rtype $end
$var reg 1 ! store $end
$upscope $end
$scope task reset $end
$upscope $end
$scope task send $end
$var reg 1 X b $end
$var reg 1 Y br $end
$var reg 32 Z file_val1_exp [31:0] $end
$var reg 32 [ file_val2_exp [31:0] $end
$var reg 32 \ imm_exp [31:0] $end
$var reg 32 ] inst_send [31:0] $end
$var reg 1 ^ it $end
$var reg 1 _ j $end
$var reg 1 ` ja $end
$var reg 1 a jr $end
$var reg 1 b lo $end
$var reg 32 c pc_send [31:0] $end
$var reg 1 d prev_br $end
$var reg 32 e prev_file_val1 [31:0] $end
$var reg 32 f prev_file_val2 [31:0] $end
$var reg 32 g prev_finalI [31:0] $end
$var reg 32 h prev_finalpc [31:0] $end
$var reg 32 i prev_imm [31:0] $end
$var reg 1 j prev_it $end
$var reg 1 k prev_ja $end
$var reg 1 l prev_jr $end
$var reg 1 m prev_lo $end
$var reg 5 n prev_reg1 [4:0] $end
$var reg 5 o prev_reg2 [4:0] $end
$var reg 5 p prev_regD [4:0] $end
$var reg 1 q prev_rt $end
$var reg 1 r prev_st $end
$var reg 5 s reg1_exp [4:0] $end
$var reg 5 t reg2_exp [4:0] $end
$var reg 5 u regD_exp [4:0] $end
$var reg 1 v rt $end
$var reg 1 w s $end
$var reg 1 x st $end
$upscope $end
$upscope $end
$enddefinitions $end
$comment Show the parameter values. $end
$dumpall
$end
#0
$dumpvars
xx
xw
xv
bx u
bx t
bx s
xr
xq
bx p
bx o
bx n
xm
xl
xk
xj
bx i
bx h
bx g
bx f
bx e
xd
bx c
xb
xa
x`
x_
x^
bx ]
bx \
bx [
bx Z
xY
xX
b0 W
b0 V
b0 U
b0 T
b0 S
0R
0Q
b0 P
b0 O
b0 N
0M
0L
0K
0J
b0 I
b0 H
b0 G
0F
b0 E
b0 D
b10011 C
b0 B
b0 A
b0 @
b0 ?
b10011 >
b0 =
b0 <
b0 ;
0:
19
b0 8
07
b0 6
b0 5
b0 4
03
02
01
b0 0
b0 /
b10011 .
b0 -
b0 ,
1+
0*
0)
0(
b0 '
b0 &
b0 %
b0 $
b0 #
0"
0!
$end
#10000
13
#20000
03
#30000
b0 .
b0 C
0+
b10111011 5
b10111011 <
b10101010 4
b10101010 ;
b111 /
b111 B
b110 0
b110 A
b101 P
b111 O
b110 N
1Q
b11001100 H
b11100110000001010110011 G
b110011 @
b11001100 8
b11001100 ?
b11100110000001010110011 6
b11100110000001010110011 =
0l
0k
0d
0r
0m
1j
0q
b0 h
b10011 g
b0 f
b0 e
b0 i
b0 p
b0 o
b0 n
b10111011 [
b10101010 Z
b0 \
b101 u
b111 t
b110 s
0w
0X
0_
0a
0`
0Y
0x
0b
0^
1v
b11001100 c
b11100110000001010110011 ]
09
13
#40000
03
#50000
b111 /
b111 B
b110 0
b110 A
b101 P
b111 O
b110 N
1Q
b11001100 -
b11001100 D
b11100110000001010110011 .
b11100110000001010110011 C
b10111011 $
b10111011 V
b10101010 &
b10101010 T
b101 #
b101 W
b111 %
b111 U
b110 '
b110 S
1"
13
#52000
b0 5
b0 <
b0 /
b0 B
b100 0
b100 A
b1000000000000100000011000110011 G
b1100 P
b0 O
b100 N
1Q
b1000000000000100000011000110011 6
b1000000000000100000011000110011 =
0j
1q
b11001100 h
b11100110000001010110011 g
b10111011 f
b10101010 e
b101 p
b111 o
b110 n
b0 [
b10101010 Z
b1100 u
b0 t
b100 s
b1000000000000100000011000110011 ]
#60000
03
#70000
b100 0
b100 A
b1100 P
b100 N
1Q
b1000000000000100000011000110011 .
b1000000000000100000011000110011 C
b0 $
b0 V
b1100 #
b1100 W
b0 %
b0 U
b100 '
b100 S
13
#72000
b10111011 5
b10111011 <
b10111011 [
b100 /
b100 B
b100 O
b1000 0
b1000 A
b10001000111000000110011 G
b0 P
b1000 N
1Q
b10001000111000000110011 6
b10001000111000000110011 =
b1000000000000100000011000110011 g
b0 f
b1100 p
b0 o
b100 n
b100 t
b10101010 Z
b0 u
b1000 s
b10001000111000000110011 ]
#80000
03
#90000
b100 /
b100 B
b1000 0
b1000 A
b100 O
b1000 N
1Q
b10001000111000000110011 .
b10001000111000000110011 C
b10111011 $
b10111011 V
b0 #
b0 W
b100 %
b100 U
b1000 '
b1000 S
13
#92000
b0 5
b0 <
b10110 I
b1000 P
1J
b0 /
b0 B
b11 0
b11 A
b1011000011000010000010011 G
b0 O
b11 N
0Q
b10011 @
b1011000011000010000010011 6
b1011000011000010000010011 =
b10001000111000000110011 g
b10111011 f
b0 p
b100 o
b1000 n
b10110 \
b1000 u
b0 [
b10101010 Z
b0 t
b11 s
1^
0v
b1011000011000010000010011 ]
#100000
03
#110000
b11 0
b11 A
b1000 P
b11 N
b10110 I
1J
b1011000011000010000010011 .
b1011000011000010000010011 C
b0 $
b0 V
b1000 #
b1000 W
b0 %
b0 U
b11 '
b11 S
b10110 ,
b10110 E
0"
1+
13
#112000
b101 0
b101 A
b1111111100101110000110010011 G
b11 P
b101 N
b11111111 I
1J
b1111111100101110000110010011 6
b1111111100101110000110010011 =
1j
0q
b1011000011000010000010011 g
b0 f
b10110 i
b1000 p
b0 o
b11 n
b10101010 Z
b11111111 \
b11 u
b101 s
b1111111100101110000110010011 ]
#120000
03
#130000
b101 0
b101 A
b11 P
b101 N
b11111111 I
1J
b1111111100101110000110010011 .
b1111111100101110000110010011 C
b11 #
b11 W
b101 '
b101 S
b11111111 ,
b11111111 E
13
#132000
b1001 0
b1001 A
b10001001001000100010011 G
b10 P
b1001 N
b100 I
1J
b10001001001000100010011 6
b10001001001000100010011 =
b1111111100101110000110010011 g
b11111111 i
b11 p
b101 n
b10101010 Z
b100 \
b10 u
b1001 s
b10001001001000100010011 ]
#140000
03
#150000
b1001 0
b1001 A
b10 P
b1001 N
b100 I
1J
b10001001001000100010011 .
b10001001001000100010011 C
b10 #
b10 W
b1001 '
b1001 S
b100 ,
b100 E
13
#152000
1M
b10 0
b10 A
b10000010010100100000011 G
b10010 P
b10 N
b100 I
0J
b11 @
b10000010010100100000011 6
b10000010010100100000011 =
b10001001001000100010011 g
b100 i
b10 p
b1001 n
b10101010 Z
b100 \
b10010 u
b10 s
1b
0^
b10000010010100100000011 ]
#160000
03
#170000
b10 0
b10 A
b10010 P
b10 N
b100 I
1M
b10000010010100100000011 .
b10000010010100100000011 C
b10010 #
b10010 W
b10 '
b10 S
1(
0+
13
#172000
b1001 0
b1001 A
b110001001010001010000011 G
b101 P
b1001 N
b1100 I
1M
b110001001010001010000011 6
b110001001010001010000011 =
1m
0j
b10000010010100100000011 g
b10010 p
b10 n
b10101010 Z
b1100 \
b101 u
b1001 s
b110001001010001010000011 ]
#180000
03
#190000
b1001 0
b1001 A
b101 P
b1001 N
b1100 I
1M
b110001001010001010000011 .
b110001001010001010000011 C
b101 #
b101 W
b1001 '
b1001 S
b1100 ,
b1100 E
13
#192000
b0 4
b0 ;
b0 0
b0 A
b10000000000011 G
b0 P
b0 N
b0 I
1M
b10000000000011 6
b10000000000011 =
b110001001010001010000011 g
b1100 i
b101 p
b1001 n
b0 Z
b0 \
b0 u
b0 s
b10000000000011 ]
#200000
03
#210000
1M
b10000000000011 .
b10000000000011 C
b0 &
b0 T
b0 #
b0 W
b0 '
b0 S
b0 ,
b0 E
13
#212000
b10111011 5
b10111011 <
b10101010 4
b10101010 ;
b10111011 [
b10101010 Z
b11 /
b11 B
b10 0
b10 A
b1100 I
b11 O
b10 N
1R
b1100010010011000100011 G
0M
b100011 @
b1100010010011000100011 6
b1100010010011000100011 =
b10000000000011 g
b0 e
b0 i
b0 p
b0 n
b1100 \
b11 t
b10 s
1x
0b
b1100010010011000100011 ]
#220000
03
#230000
b11 /
b11 B
b10 0
b10 A
b11 O
b10 N
b1100 I
1R
b1100010010011000100011 .
b1100010010011000100011 C
b10111011 $
b10111011 V
b10101010 &
b10101010 T
b11 %
b11 U
b10 '
b10 S
b1100 ,
b1100 E
1!
0(
13
#232000
b11100 /
b11100 B
b10010 0
b10010 A
b1110010010010001000100011 G
b11100 O
b10010 N
b100 I
1R
b1110010010010001000100011 6
b1110010010010001000100011 =
1r
0m
b1100010010011000100011 g
b10111011 f
b10101010 e
b1100 i
b11 o
b10 n
b10111011 [
b10101010 Z
b100 \
b11100 t
b10010 s
b1110010010010001000100011 ]
#240000
03
#250000
b11100 /
b11100 B
b10010 0
b10010 A
b11100 O
b10010 N
b100 I
1R
b1110010010010001000100011 .
b1110010010010001000100011 C
b11100 %
b11100 U
b10010 '
b10010 S
b100 ,
b100 E
13
#252000
b0 4
b0 ;
b11000 /
b11000 B
b0 0
b0 A
b1100000000010010000100011 G
b11000 O
b0 N
b1000 I
1R
b1100000000010010000100011 6
b1100000000010010000100011 =
b1110010010010001000100011 g
b100 i
b11100 o
b10010 n
b10111011 [
b0 Z
b1000 \
b11000 t
b0 s
b1100000000010010000100011 ]
#260000
03
#270000
b11000 /
b11000 B
b11000 O
b1000 I
1R
b1100000000010010000100011 .
b1100000000010010000100011 C
b0 &
b0 T
b11000 %
b11000 U
b0 '
b0 S
b1000 ,
b1000 E
13
#272000
b10101010 4
b10101010 ;
b10101010 Z
b10 0
b10 A
b10 N
1F
b1000 /
b1000 B
b11111110100000010000010011100011 G
b1000 O
b11111111111111111111111111101000 I
0R
b1100011 @
b11111110100000010000010011100011 6
b11111110100000010000010011100011 =
b1100000000010010000100011 g
b0 e
b1000 i
b11000 o
b0 n
b10 s
b10111011 [
b11111111111111111111111111101000 \
b1000 t
1Y
0x
b11111110100000010000010011100011 ]
#280000
03
#290000
b1000 /
b1000 B
b10 0
b10 A
b1000 O
b10 N
b11111111111111111111111111101000 I
1F
b11111110100000010000010011100011 .
b11111110100000010000010011100011 C
b10101010 &
b10101010 T
b1000 %
b1000 U
b10 '
b10 S
b11111111111111111111111111101000 ,
b11111111111111111111111111101000 E
11
0!
13
#292000
b0 4
b0 ;
b111 /
b111 B
b0 0
b0 A
b11111110011100000001011011100011 G
b111 O
b0 N
b11111111111111111111111111101100 I
1F
b11111110011100000001011011100011 6
b11111110011100000001011011100011 =
1d
0r
b11111110100000010000010011100011 g
b10101010 e
b11111111111111111111111111101000 i
b1000 o
b10 n
b10111011 [
b0 Z
b11111111111111111111111111101100 \
b111 t
b0 s
b11111110011100000001011011100011 ]
#300000
03
